math_psr1983/__init__.py
math_psr1983/math.py
math_package_psr1983-0.0.1.dist-info/LICENSE
math_package_psr1983-0.0.1.dist-info/METADATA
math_package_psr1983-0.0.1.dist-info/WHEEL
math_package_psr1983-0.0.1.dist-info/top_level.txt
math_package_psr1983-0.0.1.dist-info/RECORD
