Metadata-Version: 2.1
Name: math_package_psr1983
Version: 0.0.1
Summary: Math package containing add and minus functions
Author-email: Shunmuga <psr1983@gmail.com>
Project-URL: Homepage, https://github.com/pypa/sampleproject
Project-URL: Issues, https://github.com/pypa/sampleproject/issues
Classifier: Programming Language :: Python :: 3
Classifier: License :: OSI Approved :: MIT License
Classifier: Operating System :: OS Independent
Requires-Python: >=3.8
License-File: LICENSE
